webscrapetools/__init__.py
webscrapetools/keyvalue.py
webscrapetools/osaccess.py
webscrapetools/taskpool.py
webscrapetools/urlcaching.py
webscrapetools-0.5.5.dist-info/LICENSE
webscrapetools-0.5.5.dist-info/METADATA
webscrapetools-0.5.5.dist-info/WHEEL
webscrapetools-0.5.5.dist-info/top_level.txt
webscrapetools-0.5.5.dist-info/zip-safe
webscrapetools-0.5.5.dist-info/RECORD
