Metadata-Version: 2.1
Name: webscrapetools
Version: 0.5.5
Summary: A basic but fast, persistent and threadsafe caching system
Home-page: https://github.com/chris-ch/webscrapetools
Author: Christophe
Author-email: chris.perso@gmail.com
License: Apache
Download-URL: https://github.com/chris-ch/webscrapetools/webscrapetools/archive/0.5.5.tar.gz
Platform: UNKNOWN
Requires-Dist: requests (>=2.20.0)
